{
  "generator-jhipster": {
    "promptValues": {
      "packageName": "com.mycompany.myapp",
      "nativeLanguage": "en"
    },
    "jhipsterVersion": "4.10.1",
    "baseName": "app",
    "packageName": "com.mycompany.myapp",
    "packageFolder": "com/mycompany/myapp",
    "serverPort": "8080",
    "authenticationType": "jwt",
    "hibernateCache": "ehcache",
    "clusteredHttpSession": false,
    "websocket": false,
    "databaseType": "sql",
    "devDatabaseType": "mysql",
    "prodDatabaseType": "mysql",
    "searchEngine": false,
    "messageBroker": false,
    "serviceDiscoveryType": false,
    "buildTool": "maven",
    "enableSocialSignIn": true,
    "enableSwaggerCodegen": false,
    "jwtSecretKey": "27f6b623907f8f26ba454c9563a15c82292be8be",
    "clientFramework": "angular1",
    "useSass": false,
    "clientPackageManager": "yarn",
    "applicationType": "monolith",
    "testFrameworks": [],
    "jhiPrefix": "jhi",
    "enableTranslation": true,
    "nativeLanguage": "en",
    "languages": [
      "en",
      "ca"
    ]
  }
}